[
  [
    {
      "FriendlyKey": [
        "sourcenode",
        "pub_arneborg_deomcfahdc_2014"
      ]
    },
    {
      "SourceNode": {
        "Unscreened": {
          "Bibliographic": {
            "Author": {
              "item": "Arneborg, J.; Bouwman, A.; Canci, A.; Cappellini, E.; Charlton, S.; Christensen, R. J.; Collins, M. J.; Craig, O. E.; Fiddyment, S.; Fischer, R.; Fotakis, A.; Gilbert, M. T. P.; Hendy, J.; Liebert, A.; Lynnerup, N.; Mackie, M.; Montalva, N.; Olsen, J. V.; Ruehli, F.; Speller, C.; Swallow, D. M.; Trachsel, C.; Warinner, C."
            },
            "Title": {
              "item": "Direct evidence of milk consumption from ancient human dental calculus"
            },
            "Year": 2014,
            "Volume": 4,
            "DataAvailability": "NotAttachedToSource"
          }
        }
      }
    }
  ],
  []
]