[
  [
    {
      "UUID": [
        "proxiedtaxonnode",
        "0f77cb8a-6ba9-42eb-8d74-9429406942ab"
      ]
    },
    {
      "PopulationNode": "ProxiedTaxonNode"
    }
  ],
  [
    [
      {
        "UUID": [
          "proxiedtaxonnode",
          "0f77cb8a-6ba9-42eb-8d74-9429406942ab"
        ]
      },
      {
        "FriendlyKey": [
          "biodiversitydimensionnode",
          "abundance"
        ]
      },
      1,
      {
        "Population": "MeasuredBy"
      }
    ],
    [
      {
        "UUID": [
          "proxiedtaxonnode",
          "0f77cb8a-6ba9-42eb-8d74-9429406942ab"
        ]
      },
      {
        "FriendlyKey": [
          "taxonnode",
          "kingdom_placeholder from neotomadb import"
        ]
      },
      1,
      {
        "Population": "InferredAs"
      }
    ],
    [
      {
        "UUID": [
          "proxiedtaxonnode",
          "0f77cb8a-6ba9-42eb-8d74-9429406942ab"
        ]
      },
      {
        "FriendlyKey": [
          "inferencemethodnode",
          "implicit"
        ]
      },
      1,
      {
        "Population": "InferredUsing"
      }
    ],
    [
      {
        "UUID": [
          "proxiedtaxonnode",
          "0f77cb8a-6ba9-42eb-8d74-9429406942ab"
        ]
      },
      {
        "FriendlyKey": [
          "bioticproxynode",
          "morphotype_pollen_sedum"
        ]
      },
      1,
      {
        "Population": "InferredFrom"
      }
    ]
  ]
]