[
  [
    {
      "UUID": [
        "contextnode",
        "5f4af08b-d893-400b-8a29-9eb99b21fac5"
      ]
    },
    {
      "PopulationNode": {
        "ContextNode": {
          "Name": {
            "item": "Tugtuligssuaq, Melville Bay"
          },
          "SamplingLocation": {
            "Site": [
              {
                "item": 75.35347
              },
              {
                "item": -58.21491
              }
            ]
          },
          "SampleOrigin": {
            "LakeSediment": {
              "DepthRange": [
                {
                  "_depth": 0.0
                },
                {
                  "_depth": 120.0
                }
              ]
            }
          },
          "SampleLocationDescription": {
            "item": "Two connected lakes on a 20km long peninsula. Open vegetation is dominated by Cassiope tetragona and Luzula confusa with some Salix arctica and S. herbacea"
          }
        }
      }
    }
  ],
  []
]