[
  [
    {
      "UUID": [
        "proxiedtaxonnode",
        "56500960-5942-43a4-a5d1-bc8dceb3b874"
      ]
    },
    {
      "PopulationNode": "ProxiedTaxonNode"
    }
  ],
  [
    [
      {
        "UUID": [
          "proxiedtaxonnode",
          "56500960-5942-43a4-a5d1-bc8dceb3b874"
        ]
      },
      {
        "FriendlyKey": [
          "biodiversitydimensionnode",
          "abundance"
        ]
      },
      1,
      {
        "Population": "MeasuredBy"
      }
    ],
    [
      {
        "UUID": [
          "proxiedtaxonnode",
          "56500960-5942-43a4-a5d1-bc8dceb3b874"
        ]
      },
      {
        "FriendlyKey": [
          "taxonnode",
          "kingdom_placeholder from neotomadb import"
        ]
      },
      1,
      {
        "Population": "InferredAs"
      }
    ],
    [
      {
        "UUID": [
          "proxiedtaxonnode",
          "56500960-5942-43a4-a5d1-bc8dceb3b874"
        ]
      },
      {
        "FriendlyKey": [
          "inferencemethodnode",
          "implicit"
        ]
      },
      1,
      {
        "Population": "InferredUsing"
      }
    ],
    [
      {
        "UUID": [
          "proxiedtaxonnode",
          "56500960-5942-43a4-a5d1-bc8dceb3b874"
        ]
      },
      {
        "FriendlyKey": [
          "bioticproxynode",
          "morphotype_pollen_selaginella selaginoides"
        ]
      },
      1,
      {
        "Population": "InferredFrom"
      }
    ]
  ]
]