[
  [
    {
      "UUID": [
        "proxiedtaxonnode",
        "5d4e0815-78ba-4f0a-a9d6-8643eff3d683"
      ]
    },
    {
      "PopulationNode": "ProxiedTaxonNode"
    }
  ],
  [
    [
      {
        "UUID": [
          "proxiedtaxonnode",
          "5d4e0815-78ba-4f0a-a9d6-8643eff3d683"
        ]
      },
      {
        "FriendlyKey": [
          "biodiversitydimensionnode",
          "presence_absence"
        ]
      },
      1,
      {
        "Population": "MeasuredBy"
      }
    ],
    [
      {
        "UUID": [
          "proxiedtaxonnode",
          "5d4e0815-78ba-4f0a-a9d6-8643eff3d683"
        ]
      },
      {
        "FriendlyKey": [
          "taxonnode",
          "species_epirrita_autumnata_borkhausen"
        ]
      },
      1,
      {
        "Population": "InferredAs"
      }
    ],
    [
      {
        "UUID": [
          "proxiedtaxonnode",
          "5d4e0815-78ba-4f0a-a9d6-8643eff3d683"
        ]
      },
      {
        "FriendlyKey": [
          "inferencemethodnode",
          "implicit"
        ]
      },
      1,
      {
        "Population": "InferredUsing"
      }
    ],
    [
      {
        "UUID": [
          "proxiedtaxonnode",
          "5d4e0815-78ba-4f0a-a9d6-8643eff3d683"
        ]
      },
      {
        "FriendlyKey": [
          "bioticproxynode",
          "direct_betula pubescens"
        ]
      },
      1,
      {
        "Population": "InferredFrom"
      }
    ]
  ]
]