[
  [
    {
      "FriendlyKey": [
        "sourcenode",
        "pub_ khotinsky holocene of the northern eurasia_hotne_1977"
      ]
    },
    {
      "SourceNode": {
        "Unscreened": {
          "Bibliographic": {
            "Author": {
              "item": " Khotinsky Holocene of the Northern Eurasia"
            },
            "Title": {
              "item": "Holocene of the Northern Eurasia"
            },
            "Year": 1977,
            "DataAvailability": "NotAttachedToSource"
          }
        }
      }
    }
  ],
  []
]