[
  [
    {
      "UUID": [
        "contextnode",
        "c04b4b5b-4811-4eee-94bd-3b3eb0cadad9"
      ]
    },
    {
      "PopulationNode": {
        "ContextNode": {
          "Name": {
            "item": "White Spruce Upland, Churchill MB"
          },
          "SamplingLocation": {
            "Site": [
              {
                "item": 58.62
              },
              {
                "item": -93.8
              }
            ]
          },
          "SampleOrigin": "LivingOrganism"
        }
      }
    }
  ],
  []
]