[
  [
    {
      "UUID": [
        "proxiedtaxonnode",
        "bb9771e0-b2a3-43e1-9999-d5a934b4a2d2"
      ]
    },
    {
      "PopulationNode": "ProxiedTaxonNode"
    }
  ],
  [
    [
      {
        "UUID": [
          "proxiedtaxonnode",
          "bb9771e0-b2a3-43e1-9999-d5a934b4a2d2"
        ]
      },
      {
        "FriendlyKey": [
          "biodiversitydimensionnode",
          "abundance"
        ]
      },
      1,
      {
        "Population": "MeasuredBy"
      }
    ],
    [
      {
        "UUID": [
          "proxiedtaxonnode",
          "bb9771e0-b2a3-43e1-9999-d5a934b4a2d2"
        ]
      },
      {
        "FriendlyKey": [
          "taxonnode",
          "kingdom_placeholder from neotomadb import"
        ]
      },
      1,
      {
        "Population": "InferredAs"
      }
    ],
    [
      {
        "UUID": [
          "proxiedtaxonnode",
          "bb9771e0-b2a3-43e1-9999-d5a934b4a2d2"
        ]
      },
      {
        "FriendlyKey": [
          "inferencemethodnode",
          "implicit"
        ]
      },
      1,
      {
        "Population": "InferredUsing"
      }
    ],
    [
      {
        "UUID": [
          "proxiedtaxonnode",
          "bb9771e0-b2a3-43e1-9999-d5a934b4a2d2"
        ]
      },
      {
        "FriendlyKey": [
          "bioticproxynode",
          "morphotype_pollen_shepherdia canadensis"
        ]
      },
      1,
      {
        "Population": "InferredFrom"
      }
    ]
  ]
]