[
  [
    {
      "UUID": [
        "proxiedtaxonnode",
        "8413e7e1-ea29-4ae9-8595-90e4afce4654"
      ]
    },
    {
      "PopulationNode": "ProxiedTaxonNode"
    }
  ],
  [
    [
      {
        "UUID": [
          "proxiedtaxonnode",
          "8413e7e1-ea29-4ae9-8595-90e4afce4654"
        ]
      },
      {
        "FriendlyKey": [
          "biodiversitydimensionnode",
          "abundance"
        ]
      },
      1,
      {
        "Population": "MeasuredBy"
      }
    ],
    [
      {
        "UUID": [
          "proxiedtaxonnode",
          "8413e7e1-ea29-4ae9-8595-90e4afce4654"
        ]
      },
      {
        "FriendlyKey": [
          "taxonnode",
          "kingdom_placeholder from neotomadb import"
        ]
      },
      1,
      {
        "Population": "InferredAs"
      }
    ],
    [
      {
        "UUID": [
          "proxiedtaxonnode",
          "8413e7e1-ea29-4ae9-8595-90e4afce4654"
        ]
      },
      {
        "FriendlyKey": [
          "inferencemethodnode",
          "implicit"
        ]
      },
      1,
      {
        "Population": "InferredUsing"
      }
    ],
    [
      {
        "UUID": [
          "proxiedtaxonnode",
          "8413e7e1-ea29-4ae9-8595-90e4afce4654"
        ]
      },
      {
        "FriendlyKey": [
          "bioticproxynode",
          "morphotype_pollen_alnus"
        ]
      },
      1,
      {
        "Population": "InferredFrom"
      }
    ]
  ]
]