[
  [
    {
      "UUID": [
        "proxiedtaxonnode",
        "ead396f3-bdca-4f1e-b5a8-159a8c70940a"
      ]
    },
    {
      "PopulationNode": "ProxiedTaxonNode"
    }
  ],
  [
    [
      {
        "UUID": [
          "proxiedtaxonnode",
          "ead396f3-bdca-4f1e-b5a8-159a8c70940a"
        ]
      },
      {
        "FriendlyKey": [
          "biodiversitydimensionnode",
          "abundance"
        ]
      },
      1,
      {
        "Population": "MeasuredBy"
      }
    ],
    [
      {
        "UUID": [
          "proxiedtaxonnode",
          "ead396f3-bdca-4f1e-b5a8-159a8c70940a"
        ]
      },
      {
        "FriendlyKey": [
          "taxonnode",
          "kingdom_placeholder from neotomadb import"
        ]
      },
      1,
      {
        "Population": "InferredAs"
      }
    ],
    [
      {
        "UUID": [
          "proxiedtaxonnode",
          "ead396f3-bdca-4f1e-b5a8-159a8c70940a"
        ]
      },
      {
        "FriendlyKey": [
          "inferencemethodnode",
          "implicit"
        ]
      },
      1,
      {
        "Population": "InferredUsing"
      }
    ],
    [
      {
        "UUID": [
          "proxiedtaxonnode",
          "ead396f3-bdca-4f1e-b5a8-159a8c70940a"
        ]
      },
      {
        "FriendlyKey": [
          "bioticproxynode",
          "morphotype_pollen_monotropoideae"
        ]
      },
      1,
      {
        "Population": "InferredFrom"
      }
    ]
  ]
]