[
  [
    {
      "UUID": [
        "proxiedtaxonnode",
        "34007c15-26df-4126-ad93-ac2c938e4d0e"
      ]
    },
    {
      "PopulationNode": "ProxiedTaxonNode"
    }
  ],
  [
    [
      {
        "UUID": [
          "proxiedtaxonnode",
          "34007c15-26df-4126-ad93-ac2c938e4d0e"
        ]
      },
      {
        "FriendlyKey": [
          "biodiversitydimensionnode",
          "abundance"
        ]
      },
      1,
      {
        "Population": "MeasuredBy"
      }
    ],
    [
      {
        "UUID": [
          "proxiedtaxonnode",
          "34007c15-26df-4126-ad93-ac2c938e4d0e"
        ]
      },
      {
        "FriendlyKey": [
          "taxonnode",
          "kingdom_placeholder from neotomadb import"
        ]
      },
      1,
      {
        "Population": "InferredAs"
      }
    ],
    [
      {
        "UUID": [
          "proxiedtaxonnode",
          "34007c15-26df-4126-ad93-ac2c938e4d0e"
        ]
      },
      {
        "FriendlyKey": [
          "inferencemethodnode",
          "implicit"
        ]
      },
      1,
      {
        "Population": "InferredUsing"
      }
    ],
    [
      {
        "UUID": [
          "proxiedtaxonnode",
          "34007c15-26df-4126-ad93-ac2c938e4d0e"
        ]
      },
      {
        "FriendlyKey": [
          "bioticproxynode",
          "morphotype_pollen_thalictrum"
        ]
      },
      1,
      {
        "Population": "InferredFrom"
      }
    ]
  ]
]