[
  [
    {
      "UUID": [
        "proxiedtaxonnode",
        "eeb681e9-bd7b-4883-acc3-b9e7bd17ec26"
      ]
    },
    {
      "PopulationNode": "ProxiedTaxonNode"
    }
  ],
  [
    [
      {
        "UUID": [
          "proxiedtaxonnode",
          "eeb681e9-bd7b-4883-acc3-b9e7bd17ec26"
        ]
      },
      {
        "FriendlyKey": [
          "biodiversitydimensionnode",
          "abundance"
        ]
      },
      1,
      {
        "Population": "MeasuredBy"
      }
    ],
    [
      {
        "UUID": [
          "proxiedtaxonnode",
          "eeb681e9-bd7b-4883-acc3-b9e7bd17ec26"
        ]
      },
      {
        "FriendlyKey": [
          "taxonnode",
          "kingdom_placeholder from neotomadb import"
        ]
      },
      1,
      {
        "Population": "InferredAs"
      }
    ],
    [
      {
        "UUID": [
          "proxiedtaxonnode",
          "eeb681e9-bd7b-4883-acc3-b9e7bd17ec26"
        ]
      },
      {
        "FriendlyKey": [
          "inferencemethodnode",
          "implicit"
        ]
      },
      1,
      {
        "Population": "InferredUsing"
      }
    ],
    [
      {
        "UUID": [
          "proxiedtaxonnode",
          "eeb681e9-bd7b-4883-acc3-b9e7bd17ec26"
        ]
      },
      {
        "FriendlyKey": [
          "bioticproxynode",
          "morphotype_pollen_rumex longifolius"
        ]
      },
      1,
      {
        "Population": "InferredFrom"
      }
    ]
  ]
]