[
  [
    {
      "UUID": [
        "proxiedtaxonnode",
        "9b4a6578-4aaf-4790-8e7e-a6ed2f760f4a"
      ]
    },
    {
      "PopulationNode": "ProxiedTaxonNode"
    }
  ],
  [
    [
      {
        "UUID": [
          "proxiedtaxonnode",
          "9b4a6578-4aaf-4790-8e7e-a6ed2f760f4a"
        ]
      },
      {
        "FriendlyKey": [
          "biodiversitydimensionnode",
          "abundance"
        ]
      },
      1,
      {
        "Population": "MeasuredBy"
      }
    ],
    [
      {
        "UUID": [
          "proxiedtaxonnode",
          "9b4a6578-4aaf-4790-8e7e-a6ed2f760f4a"
        ]
      },
      {
        "FriendlyKey": [
          "taxonnode",
          "kingdom_placeholder from neotomadb import"
        ]
      },
      1,
      {
        "Population": "InferredAs"
      }
    ],
    [
      {
        "UUID": [
          "proxiedtaxonnode",
          "9b4a6578-4aaf-4790-8e7e-a6ed2f760f4a"
        ]
      },
      {
        "FriendlyKey": [
          "inferencemethodnode",
          "implicit"
        ]
      },
      1,
      {
        "Population": "InferredUsing"
      }
    ],
    [
      {
        "UUID": [
          "proxiedtaxonnode",
          "9b4a6578-4aaf-4790-8e7e-a6ed2f760f4a"
        ]
      },
      {
        "FriendlyKey": [
          "bioticproxynode",
          "morphotype_pollen_ranunculaceae undiff"
        ]
      },
      1,
      {
        "Population": "InferredFrom"
      }
    ]
  ]
]