[
  [
    {
      "FriendlyKey": [
        "sourcenode",
        "pub_andreev_prpna_2006"
      ]
    },
    {
      "SourceNode": {
        "Unscreened": {
          "Bibliographic": {
            "Author": {
              "item": "Andreev, A. A.; Tarasov, P. E."
            },
            "Title": {
              "item": "Pollen records, postglacial | Northern asia"
            },
            "Journal": {
              "item": "Encyclopedia of Quaternary Science"
            },
            "Year": 2006,
            "Pages": [
              2720,
              2729
            ],
            "DataAvailability": "NotAttachedToSource"
          }
        }
      }
    }
  ],
  []
]