[
  [
    {
      "UUID": [
        "proxiedtaxonnode",
        "1af255f0-0b01-4b2c-b42f-522f229f5362"
      ]
    },
    {
      "PopulationNode": "ProxiedTaxonNode"
    }
  ],
  [
    [
      {
        "UUID": [
          "proxiedtaxonnode",
          "1af255f0-0b01-4b2c-b42f-522f229f5362"
        ]
      },
      {
        "FriendlyKey": [
          "biodiversitydimensionnode",
          "abundance"
        ]
      },
      1,
      {
        "Population": "MeasuredBy"
      }
    ],
    [
      {
        "UUID": [
          "proxiedtaxonnode",
          "1af255f0-0b01-4b2c-b42f-522f229f5362"
        ]
      },
      {
        "FriendlyKey": [
          "taxonnode",
          "kingdom_placeholder from neotomadb import"
        ]
      },
      1,
      {
        "Population": "InferredAs"
      }
    ],
    [
      {
        "UUID": [
          "proxiedtaxonnode",
          "1af255f0-0b01-4b2c-b42f-522f229f5362"
        ]
      },
      {
        "FriendlyKey": [
          "inferencemethodnode",
          "implicit"
        ]
      },
      1,
      {
        "Population": "InferredUsing"
      }
    ],
    [
      {
        "UUID": [
          "proxiedtaxonnode",
          "1af255f0-0b01-4b2c-b42f-522f229f5362"
        ]
      },
      {
        "FriendlyKey": [
          "bioticproxynode",
          "morphotype_pollen_gypsophila"
        ]
      },
      1,
      {
        "Population": "InferredFrom"
      }
    ]
  ]
]