[
  [
    {
      "FriendlyKey": [
        "sourcenode",
        "pub_oksanen_hdotrrppera_2001"
      ]
    },
    {
      "SourceNode": {
        "Unscreened": {
          "Bibliographic": {
            "Author": {
              "item": "Oksanen, P. O.; Kuhry, P.; Alekseeva, R. N."
            },
            "Title": {
              "item": "Holocene development of the Rogovaya River peat plateau, European Russian Arctic"
            },
            "Journal": {
              "item": "Holocene"
            },
            "Year": 2001,
            "Volume": 11,
            "Pages": [
              25,
              40
            ],
            "DataAvailability": "NotAttachedToSource"
          }
        }
      }
    }
  ],
  []
]