[
  [
    {
      "FriendlyKey": [
        "sourcenode",
        "pub_zelikson_tfaviedta_1997"
      ]
    },
    {
      "SourceNode": {
        "Unscreened": {
          "Bibliographic": {
            "Author": {
              "item": "Zelikson, E. M."
            },
            "Title": {
              "item": "The flora and vegetation in Europe during the Allerod"
            },
            "Journal": {
              "item": "Quaternary International"
            },
            "Year": 1997,
            "Pages": [
              97,
              101
            ],
            "DataAvailability": "NotAttachedToSource"
          }
        }
      }
    }
  ],
  []
]