[
  [
    {
      "UUID": [
        "proxiedtaxonnode",
        "a2e63811-0ff0-40ff-977c-89a78177bdd2"
      ]
    },
    {
      "PopulationNode": "ProxiedTaxonNode"
    }
  ],
  [
    [
      {
        "UUID": [
          "proxiedtaxonnode",
          "a2e63811-0ff0-40ff-977c-89a78177bdd2"
        ]
      },
      {
        "FriendlyKey": [
          "biodiversitydimensionnode",
          "abundance"
        ]
      },
      1,
      {
        "Population": "MeasuredBy"
      }
    ],
    [
      {
        "UUID": [
          "proxiedtaxonnode",
          "a2e63811-0ff0-40ff-977c-89a78177bdd2"
        ]
      },
      {
        "FriendlyKey": [
          "taxonnode",
          "kingdom_placeholder from neotomadb import"
        ]
      },
      1,
      {
        "Population": "InferredAs"
      }
    ],
    [
      {
        "UUID": [
          "proxiedtaxonnode",
          "a2e63811-0ff0-40ff-977c-89a78177bdd2"
        ]
      },
      {
        "FriendlyKey": [
          "inferencemethodnode",
          "implicit"
        ]
      },
      1,
      {
        "Population": "InferredUsing"
      }
    ],
    [
      {
        "UUID": [
          "proxiedtaxonnode",
          "a2e63811-0ff0-40ff-977c-89a78177bdd2"
        ]
      },
      {
        "FriendlyKey": [
          "bioticproxynode",
          "morphotype_pollen_rubus chamaemorus"
        ]
      },
      1,
      {
        "Population": "InferredFrom"
      }
    ]
  ]
]