[
  [
    {
      "FriendlyKey": [
        "taxonnode",
        "genus_nephus"
      ]
    },
    {
      "PopulationNode": {
        "TaxonomyNode": {
          "Genus": {
            "item": "Nephus"
          }
        }
      }
    }
  ],
  [
    [
      {
        "FriendlyKey": [
          "taxonnode",
          "genus_nephus"
        ]
      },
      {
        "FriendlyKey": [
          "taxonnode",
          "family_coccinellidae"
        ]
      },
      1,
      {
        "Population": "IsA"
      }
    ]
  ]
]