[
  [
    {
      "UUID": [
        "proxiedtaxonnode",
        "3ca7d7ad-1389-4b76-a482-72576a980b80"
      ]
    },
    {
      "PopulationNode": "ProxiedTaxonNode"
    }
  ],
  [
    [
      {
        "UUID": [
          "proxiedtaxonnode",
          "3ca7d7ad-1389-4b76-a482-72576a980b80"
        ]
      },
      {
        "FriendlyKey": [
          "biodiversitydimensionnode",
          "abundance"
        ]
      },
      1,
      {
        "Population": "MeasuredBy"
      }
    ],
    [
      {
        "UUID": [
          "proxiedtaxonnode",
          "3ca7d7ad-1389-4b76-a482-72576a980b80"
        ]
      },
      {
        "FriendlyKey": [
          "taxonnode",
          "kingdom_placeholder from neotomadb import"
        ]
      },
      1,
      {
        "Population": "InferredAs"
      }
    ],
    [
      {
        "UUID": [
          "proxiedtaxonnode",
          "3ca7d7ad-1389-4b76-a482-72576a980b80"
        ]
      },
      {
        "FriendlyKey": [
          "inferencemethodnode",
          "implicit"
        ]
      },
      1,
      {
        "Population": "InferredUsing"
      }
    ],
    [
      {
        "UUID": [
          "proxiedtaxonnode",
          "3ca7d7ad-1389-4b76-a482-72576a980b80"
        ]
      },
      {
        "FriendlyKey": [
          "bioticproxynode",
          "morphotype_pollen_polemonium acutiflorum"
        ]
      },
      1,
      {
        "Population": "InferredFrom"
      }
    ]
  ]
]