[
  [
    {
      "FriendlyKey": [
        "inferencemethodnode",
        "atlas_m&#228;kel&#228; (1998) birch pollen measurements and the history of birch at bruvatnet, norwegian lapland, grana, 37:6, 358-3"
      ]
    },
    {
      "PopulationNode": {
        "InferenceMethodNode": {
          "IdentificationKeyOrAtlas": {
            "item": "Mäkelä (1998) Birch pollen measurements and the history of birch at Bruvatnet, Norwegian Lapland, Grana, 37:6, 358-3"
          }
        }
      }
    }
  ],
  []
]