[
  [
    {
      "FriendlyKey": [
        "sourcenode",
        "pub_elias_polpftblbcssrna_1992"
      ]
    },
    {
      "SourceNode": {
        "Excluded": [
          {
            "Bibliographic": {
              "Author": {
                "item": "Elias, S. A.; Short, S. K.; Phillips, R. L."
              },
              "Title": {
                "item": "Paleoecology of late-glacial peats from the Bering land bridge, Chukchi Sea shelf region, northwestern Alaska"
              },
              "Journal": {
                "item": "Quaternary Research (Orlando)"
              },
              "Year": 1992,
              "Volume": 38,
              "Pages": [
                371,
                378
              ],
              "DataAvailability": "NotAttachedToSource"
            }
          },
          "IsOceanic",
          {
            "item": "Non-marine pollen and insects from marine core"
          }
        ]
      }
    }
  ],
  []
]