[
  [
    {
      "FriendlyKey": [
        "sourcenode",
        "pub_lindholm_astpfhiosps1atntif_2009"
      ]
    },
    {
      "SourceNode": {
        "Included": [
          {
            "Bibliographic": {
              "Author": {
                "item": "Lindholm, M.; Ogurtsov, M.; Aalto, T.; Jalkanen, R.; Salminen, H."
              },
              "Title": {
                "item": "A summer temperature proxy from height increment of Scots pine since 1561 at the northern timberline in Fennoscandia"
              },
              "Journal": {
                "item": "Holocene"
              },
              "Year": 2009,
              "Volume": 19,
              "Pages": [
                1131,
                1138
              ],
              "DataAvailability": "NotAttachedToSource"
            }
          },
          "CompletedAll"
        ]
      }
    }
  ],
  [
    [
      {
        "FriendlyKey": [
          "sourcenode",
          "pub_lindholm_astpfhiosps1atntif_2009"
        ]
      },
      {
        "UUID": [
          "individualtimelinenode",
          "dbb73f40-01f9-4204-b7c8-42ca493a69eb"
        ]
      },
      1,
      {
        "Source": "HasTemporalExtent"
      }
    ]
  ]
]