[
  [
    {
      "FriendlyKey": [
        "sourcenode",
        "pub_eronen_gvospdtltmaacsocirinfl_1998"
      ]
    },
    {
      "SourceNode": {
        "Unscreened": {
          "Bibliographic": {
            "Author": {
              "item": "Eronen, M.; Kultti, S.; Lindholm, M.; Saastamoinen, S."
            },
            "Title": {
              "item": "Growth variability of Scots pine during the last two millenia and a case study of carbon isotope ratios in northern Finnish Lapland"
            },
            "Year": 1998,
            "DataAvailability": "NotAttachedToSource"
          }
        }
      }
    }
  ],
  []
]