[
  [
    {
      "FriendlyKey": [
        "sourcenode",
        "grey_mcandrews_j_sg1pdmnnedmdaldthduottoc"
      ]
    },
    {
      "SourceNode": {
        "Included": [
          {
            "GreyLiterature": {
              "Contact": {
                "FirstName": {
                  "item": "J.H."
                },
                "LastName": {
                  "item": "McAndrews"
                }
              },
              "License": "No license specified",
              "Title": {
                "item": "Samson, G. 1983. Prehistorie du Mushuau Nipi, Nouveau-Quebec: etude du mode d'adaptation a l'interier des terres hemi-arctiques. Dissertation. University of Toronto, Toronto, Ontario, Canada."
              }
            }
          },
          {
            "InProgress": []
          }
        ]
      }
    }
  ],
  [
    [
      {
        "FriendlyKey": [
          "sourcenode",
          "grey_mcandrews_j_sg1pdmnnedmdaldthduottoc"
        ]
      },
      {
        "UUID": [
          "individualtimelinenode",
          "68f3df26-336c-4195-b471-cd6765731a26"
        ]
      },
      1,
      {
        "Source": "HasTemporalExtent"
      }
    ]
  ]
]