[
  [
    {
      "UUID": [
        "individualdatenode",
        "672343ad-07fe-4b03-bfe3-3109da3b405a"
      ]
    },
    {
      "ExposureNode": {
        "DateNode": {
          "Date": {
            "RadiocarbonUncalibrated": 9620.0
          },
          "MeasurementError": {
            "DatingErrorPlusMinus": 50.0
          },
          "MaterialDated": {
            "item": "Sand with Coal"
          },
          "SampleDepth": {
            "DepthBand": [
              {
                "_depth": 160.0
              },
              {
                "_depth": 120.0
              }
            ]
          },
          "Discarded": false
        }
      }
    }
  ],
  [
    [
      {
        "UUID": [
          "individualdatenode",
          "672343ad-07fe-4b03-bfe3-3109da3b405a"
        ]
      },
      {
        "FriendlyKey": [
          "calyearnode",
          "9620ybp"
        ]
      },
      1,
      {
        "Exposure": {
          "TimeEstimate": {
            "BP": 9620.0
          }
        }
      }
    ]
  ]
]