[
  [
    {
      "UUID": [
        "proxiedtaxonnode",
        "9b6c4405-757f-448c-ad8b-67bd4a0378c3"
      ]
    },
    {
      "PopulationNode": "ProxiedTaxonNode"
    }
  ],
  [
    [
      {
        "UUID": [
          "proxiedtaxonnode",
          "9b6c4405-757f-448c-ad8b-67bd4a0378c3"
        ]
      },
      {
        "FriendlyKey": [
          "biodiversitydimensionnode",
          "abundance"
        ]
      },
      1,
      {
        "Population": "MeasuredBy"
      }
    ],
    [
      {
        "UUID": [
          "proxiedtaxonnode",
          "9b6c4405-757f-448c-ad8b-67bd4a0378c3"
        ]
      },
      {
        "FriendlyKey": [
          "taxonnode",
          "kingdom_placeholder from neotomadb import"
        ]
      },
      1,
      {
        "Population": "InferredAs"
      }
    ],
    [
      {
        "UUID": [
          "proxiedtaxonnode",
          "9b6c4405-757f-448c-ad8b-67bd4a0378c3"
        ]
      },
      {
        "FriendlyKey": [
          "inferencemethodnode",
          "implicit"
        ]
      },
      1,
      {
        "Population": "InferredUsing"
      }
    ],
    [
      {
        "UUID": [
          "proxiedtaxonnode",
          "9b6c4405-757f-448c-ad8b-67bd4a0378c3"
        ]
      },
      {
        "FriendlyKey": [
          "bioticproxynode",
          "morphotype_pollen_acer"
        ]
      },
      1,
      {
        "Population": "InferredFrom"
      }
    ]
  ]
]