[
  [
    {
      "UUID": [
        "proxiedtaxonnode",
        "29b75a85-b3b6-4e4f-a3af-8f7e017cdfc6"
      ]
    },
    {
      "PopulationNode": "ProxiedTaxonNode"
    }
  ],
  [
    [
      {
        "UUID": [
          "proxiedtaxonnode",
          "29b75a85-b3b6-4e4f-a3af-8f7e017cdfc6"
        ]
      },
      {
        "FriendlyKey": [
          "biodiversitydimensionnode",
          "abundance"
        ]
      },
      1,
      {
        "Population": "MeasuredBy"
      }
    ],
    [
      {
        "UUID": [
          "proxiedtaxonnode",
          "29b75a85-b3b6-4e4f-a3af-8f7e017cdfc6"
        ]
      },
      {
        "FriendlyKey": [
          "taxonnode",
          "kingdom_placeholder from neotomadb import"
        ]
      },
      1,
      {
        "Population": "InferredAs"
      }
    ],
    [
      {
        "UUID": [
          "proxiedtaxonnode",
          "29b75a85-b3b6-4e4f-a3af-8f7e017cdfc6"
        ]
      },
      {
        "FriendlyKey": [
          "inferencemethodnode",
          "implicit"
        ]
      },
      1,
      {
        "Population": "InferredUsing"
      }
    ],
    [
      {
        "UUID": [
          "proxiedtaxonnode",
          "29b75a85-b3b6-4e4f-a3af-8f7e017cdfc6"
        ]
      },
      {
        "FriendlyKey": [
          "bioticproxynode",
          "morphotype_pollen_caltha palustris"
        ]
      },
      1,
      {
        "Population": "InferredFrom"
      }
    ]
  ]
]