[
  [
    {
      "UUID": [
        "proxiedtaxonnode",
        "333ca369-54d0-45bd-95b0-8a3a84510823"
      ]
    },
    {
      "PopulationNode": "ProxiedTaxonNode"
    }
  ],
  [
    [
      {
        "UUID": [
          "proxiedtaxonnode",
          "333ca369-54d0-45bd-95b0-8a3a84510823"
        ]
      },
      {
        "FriendlyKey": [
          "biodiversitydimensionnode",
          "abundance"
        ]
      },
      1,
      {
        "Population": "MeasuredBy"
      }
    ],
    [
      {
        "UUID": [
          "proxiedtaxonnode",
          "333ca369-54d0-45bd-95b0-8a3a84510823"
        ]
      },
      {
        "FriendlyKey": [
          "taxonnode",
          "kingdom_placeholder from neotomadb import"
        ]
      },
      1,
      {
        "Population": "InferredAs"
      }
    ],
    [
      {
        "UUID": [
          "proxiedtaxonnode",
          "333ca369-54d0-45bd-95b0-8a3a84510823"
        ]
      },
      {
        "FriendlyKey": [
          "inferencemethodnode",
          "implicit"
        ]
      },
      1,
      {
        "Population": "InferredUsing"
      }
    ],
    [
      {
        "UUID": [
          "proxiedtaxonnode",
          "333ca369-54d0-45bd-95b0-8a3a84510823"
        ]
      },
      {
        "FriendlyKey": [
          "bioticproxynode",
          "morphotype_pollen_alismataceae"
        ]
      },
      1,
      {
        "Population": "InferredFrom"
      }
    ]
  ]
]