[
  [
    {
      "UUID": [
        "proxiedtaxonnode",
        "1c15dc3b-ff1c-4b80-be15-b79fde4bee66"
      ]
    },
    {
      "PopulationNode": "ProxiedTaxonNode"
    }
  ],
  [
    [
      {
        "UUID": [
          "proxiedtaxonnode",
          "1c15dc3b-ff1c-4b80-be15-b79fde4bee66"
        ]
      },
      {
        "FriendlyKey": [
          "biodiversitydimensionnode",
          "abundance"
        ]
      },
      1,
      {
        "Population": "MeasuredBy"
      }
    ],
    [
      {
        "UUID": [
          "proxiedtaxonnode",
          "1c15dc3b-ff1c-4b80-be15-b79fde4bee66"
        ]
      },
      {
        "FriendlyKey": [
          "taxonnode",
          "kingdom_placeholder from neotomadb import"
        ]
      },
      1,
      {
        "Population": "InferredAs"
      }
    ],
    [
      {
        "UUID": [
          "proxiedtaxonnode",
          "1c15dc3b-ff1c-4b80-be15-b79fde4bee66"
        ]
      },
      {
        "FriendlyKey": [
          "inferencemethodnode",
          "implicit"
        ]
      },
      1,
      {
        "Population": "InferredUsing"
      }
    ],
    [
      {
        "UUID": [
          "proxiedtaxonnode",
          "1c15dc3b-ff1c-4b80-be15-b79fde4bee66"
        ]
      },
      {
        "FriendlyKey": [
          "bioticproxynode",
          "morphotype_pollen_abies"
        ]
      },
      1,
      {
        "Population": "InferredFrom"
      }
    ]
  ]
]