[
  [
    {
      "FriendlyKey": [
        "sourcenode",
        "pub_niklasson_tonsine_1999"
      ]
    },
    {
      "SourceNode": {
        "Unscreened": {
          "Bibliographic": {
            "Author": {
              "item": "Niklasson, M.; Zielonka, T."
            },
            "Title": {
              "item": "The oldest Norway spruce in Northern Europe"
            },
            "Journal": {
              "item": "Svensk Botanisk Tidskrift"
            },
            "Year": 1999,
            "Volume": 93,
            "Pages": [
              287,
              293
            ],
            "DataAvailability": "NotAttachedToSource"
          }
        }
      }
    }
  ],
  []
]